audl/__init__.py
audl/__main__.py
audl/stats/__init__.py
audl/stats/endpoints/__init__.py
audl/stats/endpoints/_base.py
audl/stats/endpoints/gamestats.py
audl/stats/endpoints/playerprofile.py
audl/stats/endpoints/playerstats.py
audl/stats/endpoints/seasonschedule.py
audl/stats/endpoints/teamgamestats.py
audl/stats/endpoints/teamstats.py
audl/stats/endpoints/utils.py
audl/stats/library/__init__.py
audl/stats/library/game_event.py
audl/stats/library/parameters.py
audl/stats/static/__init__.py
audl/stats/static/constants.py
audl/stats/static/utils.py
audl/utils/__init__.py
audl/utils/players.py
tests/__init__.py
tests/stats/__init__.py
tests/stats/endpoints/__init__.py
tests/stats/endpoints/test_alltimeplayerstats.py
tests/stats/endpoints/test_gamestats.py
tests/stats/endpoints/test_playerprofile.py
tests/stats/endpoints/test_playerstats.py
tests/stats/endpoints/test_seasonschedule.py
tests/stats/endpoints/test_teamgamestats.py
tests/stats/endpoints/test_teamstats.py
tests/stats/endpoints/test_utils.py
audl-0.0.18.dist-info/METADATA
audl-0.0.18.dist-info/WHEEL
audl-0.0.18.dist-info/top_level.txt
audl-0.0.18.dist-info/RECORD
