Metadata-Version: 2.4
Name: audl
Version: 0.0.18
Summary: Unofficial audl api
Home-page: https://github.com/yukikongju/audl
Author: yukikongju
Author-email: yukikongju@outlook.com
License: MIT
Keywords: audl,audl.com,ultimate frisbee
Classifier: Programming Language :: Python :: 3
Classifier: License :: OSI Approved :: MIT License
Classifier: Operating System :: OS Independent
Requires-Python: >=3.7
Requires-Dist: pandas
Requires-Dist: requests
Requires-Dist: lxml
Requires-Dist: html5lib
Requires-Dist: pdoc3
Dynamic: author
Dynamic: author-email
Dynamic: classifier
Dynamic: description
Dynamic: description-content-type
Dynamic: home-page
Dynamic: keywords
Dynamic: license
Dynamic: requires-dist
Dynamic: requires-python
Dynamic: summary
